weles/__init__.py
weles/_version.py
weles/classifiers/ExposerClassifier.py
weles/classifiers/LinearClassifier.py
weles/classifiers/SSGNB.py
weles/classifiers/__init__.py
weles/ensembles/Cluens.py
weles/ensembles/GES.py
weles/ensembles/Geometron.py
weles/ensembles/NURS.py
weles/ensembles/RandomSubspace.py
weles/ensembles/UMCE.py
weles/ensembles/__init__.py
weles/evaluation/Analyzer.py
weles/evaluation/Evaluator.py
weles/evaluation/PairedTests.py
weles/evaluation/__init__.py
weles/meta/PCASSE.py
weles/meta/__init__.py
weles/metrics/__init__.py
weles/metrics/multiclass.py
weles/optimizers/RAO.py
weles/optimizers/__init__.py
weles/statistics/__init__.py
weles/statistics/statistics.py
weles/tests/__init__.py
weles/tests/test_classifiers.py
weles/tests/test_ensembles.py
weles/tests/test_evaluator.py
weles/tests/test_metrics.py
weles/utils/Data.py
weles/utils/__init__.py
weles/utils/diversity.py
weles/utils/nic.py
weles-0.6.4.dist-info/METADATA
weles-0.6.4.dist-info/WHEEL
weles-0.6.4.dist-info/top_level.txt
weles-0.6.4.dist-info/RECORD
